[
    {
        "name": "/v3_0/spaces/minds/core/referencespace/v1.0.0/a1655b99-82f1-420f-a3c2-fe80fd4c8588",
        "method": "GET",
        "last_request_timestamp": 1758002149.9824374,
        "start_time": 1758002149.9823875,
        "num_requests": 1,
        "num_none_requests": 0,
        "num_failures": 0,
        "total_response_time": 3223.5290989999894,
        "max_response_time": 3223.5290989999894,
        "min_response_time": 3223.5290989999894,
        "total_content_length": 2525,
        "response_times": {
            "3200.0": 1
        },
        "num_reqs_per_sec": {
            "1758002149": 1
        },
        "num_fail_per_sec": {}
    },
    {
        "name": "/v3_0/spaces/minds/core/referencespace/v1.0.0/7f39f7be-445b-47c0-9791-e971c0b6d992",
        "method": "GET",
        "last_request_timestamp": 1758002150.0167444,
        "start_time": 1758002150.016731,
        "num_requests": 1,
        "num_none_requests": 0,
        "num_failures": 0,
        "total_response_time": 3270.1079930000105,
        "max_response_time": 3270.1079930000105,
        "min_response_time": 3270.1079930000105,
        "total_content_length": 3357,
        "response_times": {
            "3300.0": 1
        },
        "num_reqs_per_sec": {
            "1758002150": 1
        },
        "num_fail_per_sec": {}
    },
    {
        "name": "/v3_0/spaces/minds/core/referencespace/v1.0.0/dafcffc5-4826-4bf1-8ff6-46b8a31ff8e2",
        "method": "GET",
        "last_request_timestamp": 1758002150.078795,
        "start_time": 1758002150.078772,
        "num_requests": 1,
        "num_none_requests": 0,
        "num_failures": 0,
        "total_response_time": 3325.6028049999886,
        "max_response_time": 3325.6028049999886,
        "min_response_time": 3325.6028049999886,
        "total_content_length": 3607,
        "response_times": {
            "3300.0": 1
        },
        "num_reqs_per_sec": {
            "1758002150": 1
        },
        "num_fail_per_sec": {}
    },
    {
        "name": "/v3_0/spaces/minds/core/referencespace/v1.0.0/tmp-fsaverage",
        "method": "GET",
        "last_request_timestamp": 1758002150.3649905,
        "start_time": 1758002150.364977,
        "num_requests": 1,
        "num_none_requests": 0,
        "num_failures": 0,
        "total_response_time": 3609.446369000011,
        "max_response_time": 3609.446369000011,
        "min_response_time": 3609.446369000011,
        "total_content_length": 3664,
        "response_times": {
            "3600.0": 1
        },
        "num_reqs_per_sec": {
            "1758002150": 1
        },
        "num_fail_per_sec": {}
    },
    {
        "name": "/v3_0/atlases",
        "method": "GET",
        "last_request_timestamp": 1758002150.467124,
        "start_time": 1758002150.4134161,
        "num_requests": 2,
        "num_none_requests": 0,
        "num_failures": 0,
        "total_response_time": 7399.062154000007,
        "max_response_time": 3730.019157000015,
        "min_response_time": 3669.0429969999914,
        "total_content_length": 6976,
        "response_times": {
            "3700.0": 2
        },
        "num_reqs_per_sec": {
            "1758002150": 2
        },
        "num_fail_per_sec": {}
    },
    {
        "name": "/v3_0/parcellations/juelich/iav/atlas/v1.0.0/4",
        "method": "GET",
        "last_request_timestamp": 1758002150.8659384,
        "start_time": 1758002150.8659246,
        "num_requests": 1,
        "num_none_requests": 0,
        "num_failures": 0,
        "total_response_time": 398.59192399998733,
        "max_response_time": 398.59192399998733,
        "min_response_time": 398.59192399998733,
        "total_content_length": 3808,
        "response_times": {
            "400.0": 1
        },
        "num_reqs_per_sec": {
            "1758002150": 1
        },
        "num_fail_per_sec": {}
    },
    {
        "name": "/v3_0/parcellations/juelich/iav/atlas/v1.0.0/79cbeaa4ee96d5d3dfe2876e9f74b3dc3d3ffb84304fb9b965b1776563a1069c",
        "method": "GET",
        "last_request_timestamp": 1758002150.875954,
        "start_time": 1758002150.8759391,
        "num_requests": 1,
        "num_none_requests": 0,
        "num_failures": 0,
        "total_response_time": 892.9548849999946,
        "max_response_time": 892.9548849999946,
        "min_response_time": 892.9548849999946,
        "total_content_length": 80016,
        "response_times": {
            "890.0": 1
        },
        "num_reqs_per_sec": {
            "1758002150": 1
        },
        "num_fail_per_sec": {}
    },
    {
        "name": "/v3_0/parcellations/minds/core/parcellationatlas/v1.0.0/94c1125b-b87e-45e4-901c-00daee7f2579-310",
        "method": "GET",
        "last_request_timestamp": 1758002151.210273,
        "start_time": 1758002151.2102551,
        "num_requests": 1,
        "num_none_requests": 0,
        "num_failures": 0,
        "total_response_time": 1192.9003369999975,
        "max_response_time": 1192.9003369999975,
        "min_response_time": 1192.9003369999975,
        "total_content_length": 184750,
        "response_times": {
            "1200.0": 1
        },
        "num_reqs_per_sec": {
            "1758002151": 1
        },
        "num_fail_per_sec": {}
    },
    {
        "name": "/v3_0/parcellations/minds/core/parcellationatlas/v1.0.0/94c1125b-b87e-45e4-901c-00daee7f2579-300",
        "method": "GET",
        "last_request_timestamp": 1758002151.2626626,
        "start_time": 1758002151.2626433,
        "num_requests": 1,
        "num_none_requests": 0,
        "num_failures": 0,
        "total_response_time": 1183.653932999988,
        "max_response_time": 1183.653932999988,
        "min_response_time": 1183.653932999988,
        "total_content_length": 142801,
        "response_times": {
            "1200.0": 1
        },
        "num_reqs_per_sec": {
            "1758002151": 1
        },
        "num_fail_per_sec": {}
    },
    {
        "name": "/v3_0/parcellations/minds/core/parcellationatlas/v1.0.0/d80fbab2-ce7f-4901-a3a2-3c8ef8a3b721",
        "method": "GET",
        "last_request_timestamp": 1758002151.2653115,
        "start_time": 1758002151.2652955,
        "num_requests": 1,
        "num_none_requests": 0,
        "num_failures": 0,
        "total_response_time": 399.2386649999844,
        "max_response_time": 399.2386649999844,
        "min_response_time": 399.2386649999844,
        "total_content_length": 10610,
        "response_times": {
            "400.0": 1
        },
        "num_reqs_per_sec": {
            "1758002151": 1
        },
        "num_fail_per_sec": {}
    },
    {
        "name": "/v3_0/parcellations/minds/core/parcellationatlas/v1.0.0/63b5794f-79a4-4464-8dc1-b32e170f3d16",
        "method": "GET",
        "last_request_timestamp": 1758002151.466166,
        "start_time": 1758002151.4661496,
        "num_requests": 1,
        "num_none_requests": 0,
        "num_failures": 0,
        "total_response_time": 590.03961800002,
        "max_response_time": 590.03961800002,
        "min_response_time": 590.03961800002,
        "total_content_length": 69432,
        "response_times": {
            "590.0": 1
        },
        "num_reqs_per_sec": {
            "1758002151": 1
        },
        "num_fail_per_sec": {}
    },
    {
        "name": "/v3_0/parcellations/minds/core/parcellationatlas/v1.0.0/141d510f-0342-4f94-ace7-c97d5f160235",
        "method": "GET",
        "last_request_timestamp": 1758002151.512393,
        "start_time": 1758002151.5123794,
        "num_requests": 1,
        "num_none_requests": 0,
        "num_failures": 0,
        "total_response_time": 301.65950699998234,
        "max_response_time": 301.65950699998234,
        "min_response_time": 301.65950699998234,
        "total_content_length": 35323,
        "response_times": {
            "300.0": 1
        },
        "num_reqs_per_sec": {
            "1758002151": 1
        },
        "num_fail_per_sec": {}
    },
    {
        "name": "/v3_0/parcellations/minds/core/parcellationatlas/v1.0.0/73f41e04-b7ee-4301-a828-4b298ad05ab8",
        "method": "GET",
        "last_request_timestamp": 1758002151.5659392,
        "start_time": 1758002151.5659251,
        "num_requests": 1,
        "num_none_requests": 0,
        "num_failures": 0,
        "total_response_time": 303.1064239999921,
        "max_response_time": 303.1064239999921,
        "min_response_time": 303.1064239999921,
        "total_content_length": 19068,
        "response_times": {
            "300.0": 1
        },
        "num_reqs_per_sec": {
            "1758002151": 1
        },
        "num_fail_per_sec": {}
    },
    {
        "name": "/v3_0/parcellations/minds/core/parcellationatlas/v1.0.0/94c1125b-b87e-45e4-901c-00daee7f2579",
        "method": "GET",
        "last_request_timestamp": 1758002151.6082458,
        "start_time": 1758002151.6082296,
        "num_requests": 1,
        "num_none_requests": 0,
        "num_failures": 0,
        "total_response_time": 1194.6680129999834,
        "max_response_time": 1194.6680129999834,
        "min_response_time": 1194.6680129999834,
        "total_content_length": 88830,
        "response_times": {
            "1200.0": 1
        },
        "num_reqs_per_sec": {
            "1758002151": 1
        },
        "num_fail_per_sec": {}
    },
    {
        "name": "/v3_0/parcellations/juelich/iav/atlas/v1.0.0/3",
        "method": "GET",
        "last_request_timestamp": 1758002151.76463,
        "start_time": 1758002151.7646165,
        "num_requests": 1,
        "num_none_requests": 0,
        "num_failures": 0,
        "total_response_time": 298.2355860000041,
        "max_response_time": 298.2355860000041,
        "min_response_time": 298.2355860000041,
        "total_content_length": 5417,
        "response_times": {
            "300.0": 1
        },
        "num_reqs_per_sec": {
            "1758002151": 1
        },
        "num_fail_per_sec": {}
    },
    {
        "name": "/v3_0/parcellations/juelich/iav/atlas/v1.0.0/6",
        "method": "GET",
        "last_request_timestamp": 1758002151.8116474,
        "start_time": 1758002151.81163,
        "num_requests": 1,
        "num_none_requests": 0,
        "num_failures": 0,
        "total_response_time": 299.03969299999744,
        "max_response_time": 299.03969299999744,
        "min_response_time": 299.03969299999744,
        "total_content_length": 7673,
        "response_times": {
            "300.0": 1
        },
        "num_reqs_per_sec": {
            "1758002151": 1
        },
        "num_fail_per_sec": {}
    },
    {
        "name": "/v3_0/parcellations/juelich/iav/atlas/v1.0.0/5",
        "method": "GET",
        "last_request_timestamp": 1758002151.865399,
        "start_time": 1758002151.8653808,
        "num_requests": 1,
        "num_none_requests": 0,
        "num_failures": 0,
        "total_response_time": 299.3142929999806,
        "max_response_time": 299.3142929999806,
        "min_response_time": 299.3142929999806,
        "total_content_length": 6084,
        "response_times": {
            "300.0": 1
        },
        "num_reqs_per_sec": {
            "1758002151": 1
        },
        "num_fail_per_sec": {}
    },
    {
        "name": "/v3_0/maps?map_type=LABELLED&parcellation_id=minds/core/parcellationatlas/v1.0.0/94c1125b-b87e-45e4-901c-00daee7f2579-310&page=1",
        "method": "GET",
        "last_request_timestamp": 1758002152.0081584,
        "start_time": 1758002152.0081458,
        "num_requests": 1,
        "num_none_requests": 0,
        "num_failures": 0,
        "total_response_time": 399.7157899999877,
        "max_response_time": 399.7157899999877,
        "min_response_time": 399.7157899999877,
        "total_content_length": 1349,
        "response_times": {
            "400.0": 1
        },
        "num_reqs_per_sec": {
            "1758002152": 1
        },
        "num_fail_per_sec": {}
    },
    {
        "name": "/v3_0/maps?map_type=LABELLED&space_id=minds/core/referencespace/v1.0.0/dafcffc5-4826-4bf1-8ff6-46b8a31ff8e2&page=1",
        "method": "GET",
        "last_request_timestamp": 1758002152.0630856,
        "start_time": 1758002152.0630686,
        "num_requests": 1,
        "num_none_requests": 0,
        "num_failures": 0,
        "total_response_time": 298.316672999988,
        "max_response_time": 298.316672999988,
        "min_response_time": 298.316672999988,
        "total_content_length": 7333,
        "response_times": {
            "300.0": 1
        },
        "num_reqs_per_sec": {
            "1758002152": 1
        },
        "num_fail_per_sec": {}
    },
    {
        "name": "/v3_0/regions?parcellation_id=minds/core/parcellationatlas/v1.0.0/94c1125b-b87e-45e4-901c-00daee7f2579-310",
        "method": "GET",
        "last_request_timestamp": 1758002152.1127996,
        "start_time": 1758002152.1127856,
        "num_requests": 1,
        "num_none_requests": 0,
        "num_failures": 0,
        "total_response_time": 300.9941850000075,
        "max_response_time": 300.9941850000075,
        "min_response_time": 300.9941850000075,
        "total_content_length": 43020,
        "response_times": {
            "300.0": 1
        },
        "num_reqs_per_sec": {
            "1758002152": 1
        },
        "num_fail_per_sec": {}
    },
    {
        "name": "/v3_0/regions?parcellation_id=minds/core/parcellationatlas/v1.0.0/94c1125b-b87e-45e4-901c-00daee7f2579-310&page=16",
        "method": "GET",
        "last_request_timestamp": 1758002152.1807652,
        "start_time": 1758002152.180753,
        "num_requests": 1,
        "num_none_requests": 0,
        "num_failures": 0,
        "total_response_time": 315.2297520000218,
        "max_response_time": 315.2297520000218,
        "min_response_time": 315.2297520000218,
        "total_content_length": 18952,
        "response_times": {
            "320.0": 1
        },
        "num_reqs_per_sec": {
            "1758002152": 1
        },
        "num_fail_per_sec": {}
    },
    {
        "name": "/v3_0/regions?parcellation_id=minds/core/parcellationatlas/v1.0.0/94c1125b-b87e-45e4-901c-00daee7f2579-310&page=14",
        "method": "GET",
        "last_request_timestamp": 1758002152.3687189,
        "start_time": 1758002152.3686953,
        "num_requests": 1,
        "num_none_requests": 0,
        "num_failures": 0,
        "total_response_time": 305.3164610000181,
        "max_response_time": 305.3164610000181,
        "min_response_time": 305.3164610000181,
        "total_content_length": 43273,
        "response_times": {
            "310.0": 1
        },
        "num_reqs_per_sec": {
            "1758002152": 1
        },
        "num_fail_per_sec": {}
    },
    {
        "name": "/v3_0/parcellations/minds/core/parcellationatlas/v1.0.0/94c1125b-b87e-45e4-901c-00daee7f2579-290",
        "method": "GET",
        "last_request_timestamp": 1758002152.3804529,
        "start_time": 1758002152.3804286,
        "num_requests": 1,
        "num_none_requests": 0,
        "num_failures": 0,
        "total_response_time": 2015.272457000009,
        "max_response_time": 2015.272457000009,
        "min_response_time": 2015.272457000009,
        "total_content_length": 290748,
        "response_times": {
            "2000.0": 1
        },
        "num_reqs_per_sec": {
            "1758002152": 1
        },
        "num_fail_per_sec": {}
    },
    {
        "name": "/v3_0/regions?parcellation_id=minds/core/parcellationatlas/v1.0.0/94c1125b-b87e-45e4-901c-00daee7f2579-310&page=15",
        "method": "GET",
        "last_request_timestamp": 1758002152.4137018,
        "start_time": 1758002152.4136887,
        "num_requests": 1,
        "num_none_requests": 0,
        "num_failures": 0,
        "total_response_time": 405.39918100000705,
        "max_response_time": 405.39918100000705,
        "min_response_time": 405.39918100000705,
        "total_content_length": 44758,
        "response_times": {
            "410.0": 1
        },
        "num_reqs_per_sec": {
            "1758002152": 1
        },
        "num_fail_per_sec": {}
    },
    {
        "name": "/v3_0/regions?parcellation_id=minds/core/parcellationatlas/v1.0.0/94c1125b-b87e-45e4-901c-00daee7f2579-310&page=13",
        "method": "GET",
        "last_request_timestamp": 1758002152.4182947,
        "start_time": 1758002152.418281,
        "num_requests": 1,
        "num_none_requests": 0,
        "num_failures": 0,
        "total_response_time": 305.3583419999768,
        "max_response_time": 305.3583419999768,
        "min_response_time": 305.3583419999768,
        "total_content_length": 43725,
        "response_times": {
            "310.0": 1
        },
        "num_reqs_per_sec": {
            "1758002152": 1
        },
        "num_fail_per_sec": {}
    },
    {
        "name": "/v3_0/regions?parcellation_id=minds/core/parcellationatlas/v1.0.0/94c1125b-b87e-45e4-901c-00daee7f2579-310&page=12",
        "method": "GET",
        "last_request_timestamp": 1758002152.488218,
        "start_time": 1758002152.488205,
        "num_requests": 1,
        "num_none_requests": 0,
        "num_failures": 0,
        "total_response_time": 307.33088799999564,
        "max_response_time": 307.33088799999564,
        "min_response_time": 307.33088799999564,
        "total_content_length": 44140,
        "response_times": {
            "310.0": 1
        },
        "num_reqs_per_sec": {
            "1758002152": 1
        },
        "num_fail_per_sec": {}
    },
    {
        "name": "/v3_0/regions?parcellation_id=minds/core/parcellationatlas/v1.0.0/94c1125b-b87e-45e4-901c-00daee7f2579-310&page=11",
        "method": "GET",
        "last_request_timestamp": 1758002152.6736848,
        "start_time": 1758002152.6736698,
        "num_requests": 1,
        "num_none_requests": 0,
        "num_failures": 0,
        "total_response_time": 304.79207300001576,
        "max_response_time": 304.79207300001576,
        "min_response_time": 304.79207300001576,
        "total_content_length": 42680,
        "response_times": {
            "300.0": 1
        },
        "num_reqs_per_sec": {
            "1758002152": 1
        },
        "num_fail_per_sec": {}
    },
    {
        "name": "/v3_0/regions?parcellation_id=minds/core/parcellationatlas/v1.0.0/94c1125b-b87e-45e4-901c-00daee7f2579-310&page=8",
        "method": "GET",
        "last_request_timestamp": 1758002152.72176,
        "start_time": 1758002152.721742,
        "num_requests": 1,
        "num_none_requests": 0,
        "num_failures": 0,
        "total_response_time": 303.311223999998,
        "max_response_time": 303.311223999998,
        "min_response_time": 303.311223999998,
        "total_content_length": 42433,
        "response_times": {
            "300.0": 1
        },
        "num_reqs_per_sec": {
            "1758002152": 1
        },
        "num_fail_per_sec": {}
    },
    {
        "name": "/v3_0/regions?parcellation_id=minds/core/parcellationatlas/v1.0.0/94c1125b-b87e-45e4-901c-00daee7f2579-310&page=7",
        "method": "GET",
        "last_request_timestamp": 1758002152.792151,
        "start_time": 1758002152.7921364,
        "num_requests": 1,
        "num_none_requests": 0,
        "num_failures": 0,
        "total_response_time": 303.8015699999903,
        "max_response_time": 303.8015699999903,
        "min_response_time": 303.8015699999903,
        "total_content_length": 42438,
        "response_times": {
            "300.0": 1
        },
        "num_reqs_per_sec": {
            "1758002152": 1
        },
        "num_fail_per_sec": {}
    },
    {
        "name": "/v3_0/regions?parcellation_id=minds/core/parcellationatlas/v1.0.0/94c1125b-b87e-45e4-901c-00daee7f2579-310&page=10",
        "method": "GET",
        "last_request_timestamp": 1758002152.7942207,
        "start_time": 1758002152.794208,
        "num_requests": 1,
        "num_none_requests": 0,
        "num_failures": 0,
        "total_response_time": 413.5315330000253,
        "max_response_time": 413.5315330000253,
        "min_response_time": 413.5315330000253,
        "total_content_length": 42419,
        "response_times": {
            "410.0": 1
        },
        "num_reqs_per_sec": {
            "1758002152": 1
        },
        "num_fail_per_sec": {}
    },
    {
        "name": "/v3_0/regions?parcellation_id=minds/core/parcellationatlas/v1.0.0/94c1125b-b87e-45e4-901c-00daee7f2579-310&page=9",
        "method": "GET",
        "last_request_timestamp": 1758002152.8181095,
        "start_time": 1758002152.818097,
        "num_requests": 1,
        "num_none_requests": 0,
        "num_failures": 0,
        "total_response_time": 404.28371400000174,
        "max_response_time": 404.28371400000174,
        "min_response_time": 404.28371400000174,
        "total_content_length": 42559,
        "response_times": {
            "400.0": 1
        },
        "num_reqs_per_sec": {
            "1758002152": 1
        },
        "num_fail_per_sec": {}
    },
    {
        "name": "/v3_0/parcellations/minds/core/parcellationatlas/v1.0.0/12fca5c5-b02c-46ce-ab9f-f12babf4c7e1",
        "method": "GET",
        "last_request_timestamp": 1758002152.842459,
        "start_time": 1758002152.8424435,
        "num_requests": 1,
        "num_none_requests": 0,
        "num_failures": 0,
        "total_response_time": 1576.9818850000092,
        "max_response_time": 1576.9818850000092,
        "min_response_time": 1576.9818850000092,
        "total_content_length": 137262,
        "response_times": {
            "1600.0": 1
        },
        "num_reqs_per_sec": {
            "1758002152": 1
        },
        "num_fail_per_sec": {}
    },
    {
        "name": "/v3_0/regions?parcellation_id=minds/core/parcellationatlas/v1.0.0/94c1125b-b87e-45e4-901c-00daee7f2579-310&page=6",
        "method": "GET",
        "last_request_timestamp": 1758002152.978936,
        "start_time": 1758002152.9789221,
        "num_requests": 1,
        "num_none_requests": 0,
        "num_failures": 0,
        "total_response_time": 305.1108230000068,
        "max_response_time": 305.1108230000068,
        "min_response_time": 305.1108230000068,
        "total_content_length": 42904,
        "response_times": {
            "310.0": 1
        },
        "num_reqs_per_sec": {
            "1758002152": 1
        },
        "num_fail_per_sec": {}
    },
    {
        "name": "/v3_0/regions?parcellation_id=minds/core/parcellationatlas/v1.0.0/94c1125b-b87e-45e4-901c-00daee7f2579-310&page=5",
        "method": "GET",
        "last_request_timestamp": 1758002153.028507,
        "start_time": 1758002153.028496,
        "num_requests": 1,
        "num_none_requests": 0,
        "num_failures": 0,
        "total_response_time": 306.555263000007,
        "max_response_time": 306.555263000007,
        "min_response_time": 306.555263000007,
        "total_content_length": 42794,
        "response_times": {
            "310.0": 1
        },
        "num_reqs_per_sec": {
            "1758002153": 1
        },
        "num_fail_per_sec": {}
    },
    {
        "name": "/v3_0/regions?parcellation_id=minds/core/parcellationatlas/v1.0.0/94c1125b-b87e-45e4-901c-00daee7f2579-310&page=4",
        "method": "GET",
        "last_request_timestamp": 1758002153.100024,
        "start_time": 1758002153.10001,
        "num_requests": 1,
        "num_none_requests": 0,
        "num_failures": 0,
        "total_response_time": 307.73752000001764,
        "max_response_time": 307.73752000001764,
        "min_response_time": 307.73752000001764,
        "total_content_length": 42641,
        "response_times": {
            "310.0": 1
        },
        "num_reqs_per_sec": {
            "1758002153": 1
        },
        "num_fail_per_sec": {}
    },
    {
        "name": "/v3_0/regions?parcellation_id=minds/core/parcellationatlas/v1.0.0/94c1125b-b87e-45e4-901c-00daee7f2579-310&page=3",
        "method": "GET",
        "last_request_timestamp": 1758002153.2104366,
        "start_time": 1758002153.210421,
        "num_requests": 1,
        "num_none_requests": 0,
        "num_failures": 0,
        "total_response_time": 416.07617600001845,
        "max_response_time": 416.07617600001845,
        "min_response_time": 416.07617600001845,
        "total_content_length": 42374,
        "response_times": {
            "420.0": 1
        },
        "num_reqs_per_sec": {
            "1758002153": 1
        },
        "num_fail_per_sec": {}
    },
    {
        "name": "/v3_0/regions?parcellation_id=minds/core/parcellationatlas/v1.0.0/94c1125b-b87e-45e4-901c-00daee7f2579-310&page=2",
        "method": "GET",
        "last_request_timestamp": 1758002153.2239764,
        "start_time": 1758002153.2239587,
        "num_requests": 1,
        "num_none_requests": 0,
        "num_failures": 0,
        "total_response_time": 405.72137600000246,
        "max_response_time": 405.72137600000246,
        "min_response_time": 405.72137600000246,
        "total_content_length": 42319,
        "response_times": {
            "410.0": 1
        },
        "num_reqs_per_sec": {
            "1758002153": 1
        },
        "num_fail_per_sec": {}
    },
    {
        "name": "/v3_0/map?map_type=LABELLED&parcellation_id=minds/core/parcellationatlas/v1.0.0/94c1125b-b87e-45e4-901c-00daee7f2579-310&space_id=minds/core/referencespace/v1.0.0/dafcffc5-4826-4bf1-8ff6-46b8a31ff8e2",
        "method": "GET",
        "last_request_timestamp": 1758002153.2446306,
        "start_time": 1758002153.2446125,
        "num_requests": 1,
        "num_none_requests": 0,
        "num_failures": 0,
        "total_response_time": 401.954432999986,
        "max_response_time": 401.954432999986,
        "min_response_time": 401.954432999986,
        "total_content_length": 50044,
        "response_times": {
            "400.0": 1
        },
        "num_reqs_per_sec": {
            "1758002153": 1
        },
        "num_fail_per_sec": {}
    },
    {
        "name": "/v3_0/feature/_types",
        "method": "GET",
        "last_request_timestamp": 1758002153.2818556,
        "start_time": 1758002153.28184,
        "num_requests": 1,
        "num_none_requests": 0,
        "num_failures": 0,
        "total_response_time": 302.770369000001,
        "max_response_time": 302.770369000001,
        "min_response_time": 302.770369000001,
        "total_content_length": 8002,
        "response_times": {
            "300.0": 1
        },
        "num_reqs_per_sec": {
            "1758002153": 1
        },
        "num_fail_per_sec": {}
    },
    {
        "name": "/v3_0/maps?map_type=LABELLED&space_id=minds/core/referencespace/v1.0.0/a1655b99-82f1-420f-a3c2-fe80fd4c8588&page=1",
        "method": "GET",
        "last_request_timestamp": 1758002153.3308938,
        "start_time": 1758002153.3308792,
        "num_requests": 1,
        "num_none_requests": 0,
        "num_failures": 0,
        "total_response_time": 302.1645670000055,
        "max_response_time": 302.1645670000055,
        "min_response_time": 302.1645670000055,
        "total_content_length": 1289,
        "response_times": {
            "300.0": 1
        },
        "num_reqs_per_sec": {
            "1758002153": 1
        },
        "num_fail_per_sec": {}
    },
    {
        "name": "/v3_0/regions?parcellation_id=minds/core/parcellationatlas/v1.0.0/94c1125b-b87e-45e4-901c-00daee7f2579-290",
        "method": "GET",
        "last_request_timestamp": 1758002153.4058278,
        "start_time": 1758002153.4058142,
        "num_requests": 1,
        "num_none_requests": 0,
        "num_failures": 0,
        "total_response_time": 305.6630289999873,
        "max_response_time": 305.6630289999873,
        "min_response_time": 305.6630289999873,
        "total_content_length": 42337,
        "response_times": {
            "310.0": 1
        },
        "num_reqs_per_sec": {
            "1758002153": 1
        },
        "num_fail_per_sec": {}
    },
    {
        "name": "/v3_0/regions?parcellation_id=minds/core/parcellationatlas/v1.0.0/94c1125b-b87e-45e4-901c-00daee7f2579-290&page=9",
        "method": "GET",
        "last_request_timestamp": 1758002153.5859203,
        "start_time": 1758002153.5859065,
        "num_requests": 1,
        "num_none_requests": 0,
        "num_failures": 0,
        "total_response_time": 303.9232010000035,
        "max_response_time": 303.9232010000035,
        "min_response_time": 303.9232010000035,
        "total_content_length": 42785,
        "response_times": {
            "300.0": 1
        },
        "num_reqs_per_sec": {
            "1758002153": 1
        },
        "num_fail_per_sec": {}
    },
    {
        "name": "/v3_0/regions?parcellation_id=minds/core/parcellationatlas/v1.0.0/94c1125b-b87e-45e4-901c-00daee7f2579-290&page=12",
        "method": "GET",
        "last_request_timestamp": 1758002153.623683,
        "start_time": 1758002153.6236663,
        "num_requests": 1,
        "num_none_requests": 0,
        "num_failures": 0,
        "total_response_time": 413.03437400000576,
        "max_response_time": 413.03437400000576,
        "min_response_time": 413.03437400000576,
        "total_content_length": 55,
        "response_times": {
            "410.0": 1
        },
        "num_reqs_per_sec": {
            "1758002153": 1
        },
        "num_fail_per_sec": {}
    },
    {
        "name": "/v3_0/regions?parcellation_id=minds/core/parcellationatlas/v1.0.0/94c1125b-b87e-45e4-901c-00daee7f2579-290&page=11",
        "method": "GET",
        "last_request_timestamp": 1758002153.6304553,
        "start_time": 1758002153.630442,
        "num_requests": 1,
        "num_none_requests": 0,
        "num_failures": 0,
        "total_response_time": 406.31928199999834,
        "max_response_time": 406.31928199999834,
        "min_response_time": 406.31928199999834,
        "total_content_length": 9235,
        "response_times": {
            "410.0": 1
        },
        "num_reqs_per_sec": {
            "1758002153": 1
        },
        "num_fail_per_sec": {}
    },
    {
        "name": "/v3_0/regions?parcellation_id=minds/core/parcellationatlas/v1.0.0/94c1125b-b87e-45e4-901c-00daee7f2579-290&page=8",
        "method": "GET",
        "last_request_timestamp": 1758002153.6370635,
        "start_time": 1758002153.6370487,
        "num_requests": 1,
        "num_none_requests": 0,
        "num_failures": 0,
        "total_response_time": 306.01144400000635,
        "max_response_time": 306.01144400000635,
        "min_response_time": 306.01144400000635,
        "total_content_length": 42642,
        "response_times": {
            "310.0": 1
        },
        "num_reqs_per_sec": {
            "1758002153": 1
        },
        "num_fail_per_sec": {}
    },
    {
        "name": "/v3_0/regions?parcellation_id=minds/core/parcellationatlas/v1.0.0/94c1125b-b87e-45e4-901c-00daee7f2579-290&page=10",
        "method": "GET",
        "last_request_timestamp": 1758002153.651171,
        "start_time": 1758002153.651157,
        "num_requests": 1,
        "num_none_requests": 0,
        "num_failures": 0,
        "total_response_time": 406.3672939999776,
        "max_response_time": 406.3672939999776,
        "min_response_time": 406.3672939999776,
        "total_content_length": 43222,
        "response_times": {
            "410.0": 1
        },
        "num_reqs_per_sec": {
            "1758002153": 1
        },
        "num_fail_per_sec": {}
    },
    {
        "name": "/v3_0/regions?parcellation_id=minds/core/parcellationatlas/v1.0.0/94c1125b-b87e-45e4-901c-00daee7f2579-290&page=7",
        "method": "GET",
        "last_request_timestamp": 1758002153.7125149,
        "start_time": 1758002153.7124991,
        "num_requests": 1,
        "num_none_requests": 0,
        "num_failures": 0,
        "total_response_time": 306.5388320000011,
        "max_response_time": 306.5388320000011,
        "min_response_time": 306.5388320000011,
        "total_content_length": 42683,
        "response_times": {
            "310.0": 1
        },
        "num_reqs_per_sec": {
            "1758002153": 1
        },
        "num_fail_per_sec": {}
    },
    {
        "name": "/v3_0/regions?parcellation_id=minds/core/parcellationatlas/v1.0.0/94c1125b-b87e-45e4-901c-00daee7f2579-290&page=6",
        "method": "GET",
        "last_request_timestamp": 1758002153.8934014,
        "start_time": 1758002153.893386,
        "num_requests": 1,
        "num_none_requests": 0,
        "num_failures": 0,
        "total_response_time": 307.34016900001393,
        "max_response_time": 307.34016900001393,
        "min_response_time": 307.34016900001393,
        "total_content_length": 42806,
        "response_times": {
            "310.0": 1
        },
        "num_reqs_per_sec": {
            "1758002153": 1
        },
        "num_fail_per_sec": {}
    },
    {
        "name": "/v3_0/regions?parcellation_id=minds/core/parcellationatlas/v1.0.0/94c1125b-b87e-45e4-901c-00daee7f2579-290&page=3",
        "method": "GET",
        "last_request_timestamp": 1758002153.9435275,
        "start_time": 1758002153.9435115,
        "num_requests": 1,
        "num_none_requests": 0,
        "num_failures": 0,
        "total_response_time": 306.3202450000233,
        "max_response_time": 306.3202450000233,
        "min_response_time": 306.3202450000233,
        "total_content_length": 42663,
        "response_times": {
            "310.0": 1
        },
        "num_reqs_per_sec": {
            "1758002153": 1
        },
        "num_fail_per_sec": {}
    },
    {
        "name": "/v3_0/regions?parcellation_id=minds/core/parcellationatlas/v1.0.0/94c1125b-b87e-45e4-901c-00daee7f2579-290&page=5",
        "method": "GET",
        "last_request_timestamp": 1758002154.0375373,
        "start_time": 1758002154.0375245,
        "num_requests": 1,
        "num_none_requests": 0,
        "num_failures": 0,
        "total_response_time": 412.7589779999994,
        "max_response_time": 412.7589779999994,
        "min_response_time": 412.7589779999994,
        "total_content_length": 42794,
        "response_times": {
            "410.0": 1
        },
        "num_reqs_per_sec": {
            "1758002154": 1
        },
        "num_fail_per_sec": {}
    },
    {
        "name": "/v3_0/map?map_type=LABELLED&parcellation_id=minds/core/parcellationatlas/v1.0.0/94c1125b-b87e-45e4-901c-00daee7f2579-290&space_id=minds/core/referencespace/v1.0.0/a1655b99-82f1-420f-a3c2-fe80fd4c8588",
        "method": "GET",
        "last_request_timestamp": 1758002154.041111,
        "start_time": 1758002154.0410988,
        "num_requests": 1,
        "num_none_requests": 0,
        "num_failures": 1,
        "total_response_time": 328.09841000002393,
        "max_response_time": 328.09841000002393,
        "min_response_time": 328.09841000002393,
        "total_content_length": 67,
        "response_times": {
            "330.0": 1
        },
        "num_reqs_per_sec": {
            "1758002154": 1
        },
        "num_fail_per_sec": {
            "1758002154": 1
        }
    },
    {
        "name": "/v3_0/regions?parcellation_id=minds/core/parcellationatlas/v1.0.0/94c1125b-b87e-45e4-901c-00daee7f2579-290&page=4",
        "method": "GET",
        "last_request_timestamp": 1758002154.0432744,
        "start_time": 1758002154.0432646,
        "num_requests": 1,
        "num_none_requests": 0,
        "num_failures": 0,
        "total_response_time": 412.71082399998704,
        "max_response_time": 412.71082399998704,
        "min_response_time": 412.71082399998704,
        "total_content_length": 43023,
        "response_times": {
            "410.0": 1
        },
        "num_reqs_per_sec": {
            "1758002154": 1
        },
        "num_fail_per_sec": {}
    },
    {
        "name": "/v3_0/regions?parcellation_id=minds/core/parcellationatlas/v1.0.0/94c1125b-b87e-45e4-901c-00daee7f2579-290&page=2",
        "method": "GET",
        "last_request_timestamp": 1758002154.0486202,
        "start_time": 1758002154.0486076,
        "num_requests": 1,
        "num_none_requests": 0,
        "num_failures": 0,
        "total_response_time": 397.2628120000081,
        "max_response_time": 397.2628120000081,
        "min_response_time": 397.2628120000081,
        "total_content_length": 42452,
        "response_times": {
            "400.0": 1
        },
        "num_reqs_per_sec": {
            "1758002154": 1
        },
        "num_fail_per_sec": {}
    },
    {
        "name": "/v3_0/map?map_type=LABELLED&parcellation_id=minds/core/parcellationatlas/v1.0.0/94c1125b-b87e-45e4-901c-00daee7f2579-310&space_id=minds/core/referencespace/v1.0.0/a1655b99-82f1-420f-a3c2-fe80fd4c8588",
        "method": "GET",
        "last_request_timestamp": 1758002154.214048,
        "start_time": 1758002154.2140338,
        "num_requests": 1,
        "num_none_requests": 0,
        "num_failures": 1,
        "total_response_time": 320.47746700001767,
        "max_response_time": 320.47746700001767,
        "min_response_time": 320.47746700001767,
        "total_content_length": 67,
        "response_times": {
            "320.0": 1
        },
        "num_reqs_per_sec": {
            "1758002154": 1
        },
        "num_fail_per_sec": {
            "1758002154": 1
        }
    }
]